{
  "version": 2,
  "extractor": "papercropper",
  "tables": [
    {
      "url": "assets/tables/acl-2026-long/anthology-2026.acl-long.259/table-001.webp",
      "caption": "",
      "page": 0,
      "index": 1,
      "width": 1115,
      "height": 950,
      "label": "Table"
    },
    {
      "url": "assets/tables/acl-2026-long/anthology-2026.acl-long.259/table-002.webp",
      "caption": "",
      "page": 0,
      "index": 2,
      "width": 1675,
      "height": 589,
      "label": "Table"
    },
    {
      "url": "assets/tables/acl-2026-long/anthology-2026.acl-long.259/table-003.webp",
      "caption": "",
      "page": 0,
      "index": 3,
      "width": 1682,
      "height": 702,
      "label": "Table"
    },
    {
      "url": "assets/tables/acl-2026-long/anthology-2026.acl-long.259/table-004.webp",
      "caption": "",
      "page": 0,
      "index": 4,
      "width": 1683,
      "height": 650,
      "label": "Table"
    },
    {
      "url": "assets/tables/acl-2026-long/anthology-2026.acl-long.259/table-005.webp",
      "caption": "",
      "page": 0,
      "index": 5,
      "width": 1677,
      "height": 757,
      "label": "Table"
    },
    {
      "url": "assets/tables/acl-2026-long/anthology-2026.acl-long.259/table-006.webp",
      "caption": "",
      "page": 0,
      "index": 6,
      "width": 1678,
      "height": 616,
      "label": "Table"
    },
    {
      "url": "assets/tables/acl-2026-long/anthology-2026.acl-long.259/table-007.webp",
      "caption": "",
      "page": 0,
      "index": 7,
      "width": 1679,
      "height": 1106,
      "label": "Table"
    },
    {
      "url": "assets/tables/acl-2026-long/anthology-2026.acl-long.259/table-008.webp",
      "caption": "",
      "page": 0,
      "index": 8,
      "width": 1681,
      "height": 1048,
      "label": "Table"
    },
    {
      "url": "assets/tables/acl-2026-long/anthology-2026.acl-long.259/table-009.webp",
      "caption": "",
      "page": 0,
      "index": 9,
      "width": 1559,
      "height": 960,
      "label": "Table"
    },
    {
      "url": "assets/tables/acl-2026-long/anthology-2026.acl-long.259/table-010.webp",
      "caption": "",
      "page": 0,
      "index": 10,
      "width": 1688,
      "height": 701,
      "label": "Table"
    },
    {
      "url": "assets/tables/acl-2026-long/anthology-2026.acl-long.259/table-011.webp",
      "caption": "",
      "page": 0,
      "index": 11,
      "width": 1673,
      "height": 1843,
      "label": "Table"
    },
    {
      "url": "assets/tables/acl-2026-long/anthology-2026.acl-long.259/table-012.webp",
      "caption": "",
      "page": 0,
      "index": 12,
      "width": 1693,
      "height": 251,
      "label": "Table"
    },
    {
      "url": "assets/tables/acl-2026-long/anthology-2026.acl-long.259/table-013.webp",
      "caption": "",
      "page": 0,
      "index": 13,
      "width": 1693,
      "height": 198,
      "label": "Table"
    }
  ]
}